dconfjson/__init__.py
dconfjson/to_dconf.py
dconfjson/to_json.py
dconfjson-0.2.4.dist-info/LICENCE
dconfjson-0.2.4.dist-info/METADATA
dconfjson-0.2.4.dist-info/WHEEL
dconfjson-0.2.4.dist-info/entry_points.txt
dconfjson-0.2.4.dist-info/top_level.txt
dconfjson-0.2.4.dist-info/zip-safe
dconfjson-0.2.4.dist-info/RECORD
