Metadata-Version: 2.1
Name: dconfjson
Version: 0.2.4
Summary: Convert gnome settings between binary conf files and json
Home-page: https://github.com/saberd/dconfjson
Author: saberd
Author-email: mail@saberd.com
License: BSD 3-Clause License
Keywords: ubuntu,gnome,config,dconf,json
Classifier: Topic :: Desktop Environment :: Gnome
Classifier: Programming Language :: Python :: 3
Classifier: License :: OSI Approved :: MIT License
Classifier: Topic :: Utilities
License-File: LICENCE
